LICENSE
README.md
setup.py
dz_tap_mongodb.egg-info/PKG-INFO
dz_tap_mongodb.egg-info/SOURCES.txt
dz_tap_mongodb.egg-info/dependency_links.txt
dz_tap_mongodb.egg-info/entry_points.txt
dz_tap_mongodb.egg-info/requires.txt
dz_tap_mongodb.egg-info/top_level.txt
tap_mongodb/__init__.py
tap_mongodb/config_utils.py
tap_mongodb/db_utils.py
tap_mongodb/errors.py
tap_mongodb/stream_utils.py
tap_mongodb/sync_strategies/change_streams.py
tap_mongodb/sync_strategies/common.py
tap_mongodb/sync_strategies/full_table.py
tap_mongodb/sync_strategies/incremental.py